enalog/__init__.py
enalog-0.2.1.dist-info/WHEEL
enalog-0.2.1.dist-info/METADATA
enalog-0.2.1.dist-info/RECORD
