Metadata-Version: 2.1
Name: enalog
Version: 0.2.1
Summary: Python package for sending events to EnaLog
Author: Sam Newby
Author-email: sam.newby19@gmail.com
Requires-Python: >=3.9,<4.0
Classifier: Programming Language :: Python :: 3
Classifier: Programming Language :: Python :: 3.9
Classifier: Programming Language :: Python :: 3.10
Classifier: Programming Language :: Python :: 3.11
Requires-Dist: requests (>=2.28.2,<3.0.0)
